infi.eventlog-0.1.11-py2.7-nspkg.pth
infi/eventlog/__init__.py
infi/eventlog/__version__.py
infi/eventlog/c_api/__init__.py
infi/eventlog/c_api/mock.py
infi/eventlog/facade/__init__.py
infi/eventlog/tests/__init__.py
infi.eventlog-0.1.11.dist-info/LICENSE
infi.eventlog-0.1.11.dist-info/METADATA
infi.eventlog-0.1.11.dist-info/WHEEL
infi.eventlog-0.1.11.dist-info/entry_points.txt
infi.eventlog-0.1.11.dist-info/namespace_packages.txt
infi.eventlog-0.1.11.dist-info/top_level.txt
infi.eventlog-0.1.11.dist-info/RECORD
