Metadata-Version: 2.1
Name: infi.eventlog
Version: 0.1.11
Summary: Bindings to Windows Event Log
Home-page: https://github.com/Infinidat/infi.eventlog
Author: Arnon Yaari
Author-email: arnony@infinidat.com
License: BSD
Platform: UNKNOWN
Classifier: Intended Audience :: Developers
Classifier: Intended Audience :: System Administrators
Classifier: License :: OSI Approved :: BSD License
Classifier: Operating System :: OS Independent
Classifier: Programming Language :: Python :: 2
Classifier: Programming Language :: Python :: 3
Classifier: Topic :: Software Development :: Libraries :: Python Modules
Requires-Dist: infi.cwrap
Requires-Dist: infi.pyutils
Requires-Dist: infi.wioctl
Requires-Dist: setuptools
Requires-Dist: xmltodict (>=0.8.4)
